registrasion/__init__.py
registrasion/admin.py
registrasion/apps.py
registrasion/exceptions.py
registrasion/forms.py
registrasion/urls.py
registrasion/util.py
registrasion/views.py
registrasion/controllers/__init__.py
registrasion/controllers/cart.py
registrasion/controllers/category.py
registrasion/controllers/conditions.py
registrasion/controllers/credit_note.py
registrasion/controllers/discount.py
registrasion/controllers/for_id.py
registrasion/controllers/invoice.py
registrasion/controllers/product.py
registrasion/migrations/0001_initial.py
registrasion/migrations/__init__.py
registrasion/models/__init__.py
registrasion/models/commerce.py
registrasion/models/conditions.py
registrasion/models/inventory.py
registrasion/models/people.py
registrasion/templatetags/__init__.py
registrasion/templatetags/registrasion_tags.py
registrasion/tests/__init__.py
registrasion/tests/controller_helpers.py
registrasion/tests/patch_datetime.py
registrasion/tests/test_cart.py
registrasion/tests/test_ceilings.py
registrasion/tests/test_discount.py
registrasion/tests/test_flag.py
registrasion/tests/test_invoice.py
registrasion/tests/test_refund.py
registrasion/tests/test_voucher.py
registrasion-0.1.1.dist-info/DESCRIPTION.rst
registrasion-0.1.1.dist-info/METADATA
registrasion-0.1.1.dist-info/RECORD
registrasion-0.1.1.dist-info/WHEEL
registrasion-0.1.1.dist-info/dependency_links.txt
registrasion-0.1.1.dist-info/metadata.json
registrasion-0.1.1.dist-info/top_level.txt
