Metadata-Version: 2.0
Name: registrasion
Version: 0.1.1
Summary: A registration app for the Symposion conference management system.
Home-page: http://github.com/chrisjrn/registrasion/
Author: Christopher Neugebauer
Author-email: _@chrisjrn.com
License: UNKNOWN
Platform: UNKNOWN
Classifier: Development Status :: 3 - Alpha
Classifier: Programming Language :: Python
Classifier: Framework :: Django
Classifier: Intended Audience :: Developers
Classifier: Natural Language :: English
Classifier: License :: OSI Approved :: Apache Software License
Requires-Dist: django-nested-admin (==2.2.6)
Requires-Dist: symposion (==1.0b2.dev3)
